{
  "display_name": "Best Buy",
  "employee_count": 85000,
  "financial_data_updated": "2026-02-23T15:55:26Z",
  "fortune_rank": 108,
  "founded_year": 1966,
  "headquarters": "Richfield, Minnesota, United States",
  "industry": "Consumer Discretionary",
  "industry_category": "consumer_discretionary",
  "industry_subcategory": null,
  "is_public": true,
  "last_updated": "2026-02-23T03:23:46Z",
  "market_cap_usd": 13030480896,
  "name": "Best Buy Co., Inc.",
  "slug": "best-buy",
  "summary": "Best Buy Co., Inc. is a multinational retailer of consumer electronics, home appliances, and related products and services. The company operates a large network of physical stores and an e-commerce platform. Its offerings include a wide range of technology products, entertainment items, and support services.",
  "ticker": "BBY",
  "website": "https://www.bestbuy.com"
}
