{
  "display_name": "Corning",
  "employee_count": 69000,
  "fortune_rank": 324,
  "founded_year": 1851,
  "headquarters": "Corning, New York, United States",
  "industry": "Materials",
  "industry_category": "materials",
  "industry_subcategory": null,
  "is_public": true,
  "last_updated": "2026-03-19T17:47:44Z",
  "market_cap_usd": 33000000000,
  "name": "Corning Incorporated",
  "slug": "corning",
  "summary": "Corning Incorporated is a global materials science company that develops and manufactures specialty glass, ceramics, and related materials. Its key business segments include Optical Communications, Display Technologies, Environmental Technologies, Life Sciences, and Specialty Materials. Corning's products are used in a wide range of applications, including telecommunications, mobile consumer electronics, automotive, and life sciences.",
  "ticker": "GLW",
  "website": "https://www.corning.com"
}
