{
  "display_name": "Devon Energy",
  "employee_count": 1700,
  "fortune_rank": 267,
  "founded_year": 1971,
  "headquarters": "Oklahoma City, Oklahoma, United States",
  "industry": "Energy",
  "industry_category": "energy",
  "industry_subcategory": null,
  "is_public": true,
  "last_updated": "2026-03-19T17:48:54Z",
  "market_cap_usd": 27000000000,
  "name": "Devon Energy Corporation",
  "slug": "devon-energy",
  "summary": "Devon Energy Corporation is an independent energy company engaged in oil and natural gas exploration and production. The company's operations are primarily focused in the United States, with significant assets in the Delaware Basin, Anadarko Basin, Eagle Ford, Powder River Basin, and Williston Basin. Devon Energy is committed to delivering superior shareholder returns through a disciplined capital allocation strategy and operational excellence.",
  "ticker": "DVN",
  "website": "https://www.devonenergy.com"
}
