{
  "display_name": "Hertz",
  "employee_count": 21000,
  "fortune_rank": 440,
  "founded_year": 1925,
  "headquarters": "Estero, Florida, United States",
  "industry": "Consumer Discretionary",
  "industry_category": "consumer_discretionary",
  "industry_subcategory": null,
  "is_public": true,
  "last_updated": "2026-03-19T17:56:24Z",
  "market_cap_usd": 5000000000,
  "name": "Hertz Global Holdings, Inc.",
  "slug": "hertz",
  "summary": "Hertz Global Holdings, Inc. is a car rental company. It operates through its subsidiary, The Hertz Corporation, offering a wide range of vehicle rental services. The company provides services to leisure and business customers through its brands, including Hertz, Dollar, and Thrifty.",
  "ticker": "HTZ",
  "website": "https://www.hertz.com"
}
