{
  "display_name": "Hewlett Packard Enterprise",
  "employee_count": 67000,
  "financial_data_updated": "2026-02-23T15:55:26Z",
  "fortune_rank": 143,
  "founded_year": 2015,
  "headquarters": "Spring, Texas, United States",
  "industry": "Information Technology",
  "industry_category": "information_technology",
  "industry_subcategory": "hardware_devices",
  "is_public": true,
  "last_updated": "2026-02-23T03:30:39Z",
  "market_cap_usd": 27311220736,
  "name": "Hewlett Packard Enterprise Company",
  "slug": "hpe",
  "summary": "Hewlett Packard Enterprise Company is a global technology company that provides a broad portfolio of enterprise IT solutions. Its key business segments include Intelligent Edge, High Performance Computing & Analytics, and Financial Services. HPE serves customers in over 150 countries.",
  "ticker": "HPE",
  "website": "https://www.hpe.com"
}
